chromedriverversion/__init__.py
chromedriverversion/getDriver.py
chromedriverversion-0.4.0.dist-info/LICENSE
chromedriverversion-0.4.0.dist-info/WHEEL
chromedriverversion-0.4.0.dist-info/METADATA
chromedriverversion-0.4.0.dist-info/RECORD
